{
    "name": "张远",
    "gender": "male",
    "birth": "1945年3月12日",
    "death": "2010年8月23日",
    "bio": "家族创始人，曾担任教师40余年，为人正直，深受族人尊敬。",
    "children": [
        {
            "name": "张建国",
            "gender": "male",
            "birth": "1970年5月3日",
            "bio": "长子，企业家，创办建筑材料公司。热心公益。",
            "spouse": "李红梅",
            "children": [
                {
                    "name": "张宇航",
                    "gender": "male",
                    "birth": "1995年11月8日",
                    "bio": "软件工程师，现居上海。热爱编程和摄影。",
                    "spouse": "陈思思"
                }
            ]
        },
        {
            "name": "张建华",
            "gender": "male",
            "birth": "1973年9月15日",
            "bio": "次子，医生，心血管疾病专家。",
            "spouse": "王丽娜",
            "children": [
                {
                    "name": "张雨欣",
                    "gender": "female",
                    "birth": "1998年7月22日",
                    "bio": "在读研究生，专业为生物工程。"
                },
                {
                    "name": "张浩宇",
                    "gender": "male",
                    "birth": "2001年2月14日",
                    "bio": "大学生，计算机专业。"
                }
            ]
        }
    ]
}
